catpictures/__init__.py
catpictures/cat.py
catpictures-1.1.dist-info/LICENSE
catpictures-1.1.dist-info/METADATA
catpictures-1.1.dist-info/WHEEL
catpictures-1.1.dist-info/top_level.txt
catpictures-1.1.dist-info/RECORD
