Metadata-Version: 2.1
Name: catpictures
Version: 1.1
Summary: Open a picture of a cat in a new tab on your browser
Home-page: https://github.com/GiacomoLaw/catpictures
Author: Giacomo Lawrance
Author-email: thenerdystudent@gmail.com
License: UNKNOWN
Platform: UNKNOWN
Classifier: Programming Language :: Python :: 3
Classifier: Operating System :: OS Independent
